Metadata-Version: 2.1
Name: Randomcardpickerlite
Version: 0.0.1
Summary: pick a random card
Home-page: UNKNOWN
Author: Borys Paisny
Author-email: BorysPiasny@gmail.com
License: UNKNOWN
Platform: UNKNOWN
